LICENSE
MANIFEST.in
README.rst
setup.cfg
setup.py
stakkr/__init__.py
stakkr/actions.py
stakkr/aliases.py
stakkr/cli.py
stakkr/command.py
stakkr/configreader.py
stakkr/docker_actions.py
stakkr/file_utils.py
stakkr/proxy.py
stakkr/services.py
stakkr/setup.py
stakkr/stakkr_compose.py
stakkr.egg-info/PKG-INFO
stakkr.egg-info/SOURCES.txt
stakkr.egg-info/dependency_links.txt
stakkr.egg-info/entry_points.txt
stakkr.egg-info/requires.txt
stakkr.egg-info/top_level.txt
stakkr/static/config_default.yml
stakkr/static/config_schema.yml
stakkr/static/docker-compose.subnet.yml
stakkr/static/docker-compose.yml
stakkr/static/proxy/config.yml
stakkr/static/proxy/traefik.yml
stakkr/static/proxy/ssl/traefik.localhost.crt
stakkr/static/proxy/ssl/traefik.localhost.key
stakkr/static/recipes/lamp.yml
stakkr/static/recipes/lemp.yml
stakkr/static/recipes/lepp.yml
stakkr/static/recipes/symfony.yml
stakkr/static/recipes/wordpress.yml
stakkr/static/services/portainer.yml
stakkr/tpls/bash_completion
stakkr/tpls/stakkr.yml.tpl
stakkr/tpls/conf/mysql-override/mysqld.cnf
stakkr/tpls/conf/php-fpm-override/README
stakkr/tpls/conf/php-fpm-override/example.conf
stakkr/tpls/conf/xhgui-override/config.php
stakkr/tpls/home/www-data/.bashrc