Metadata-Version: 2.1
Name: stakkr
Version: 5.0
Summary:  A configurable stack based on docker to run any combination of services (PHP, MySQL, Apache, Nginx, Mongo, etc..)
Home-page: http://github.com/stakkr-org/stakkr
Author: Emmanuel Dyan
Author-email: emmanueldyan@gmail.com
License: Apache 2.0
Keywords: docker,docker-compose,python,stack,development,lamp,vagrant
Platform: UNKNOWN
Classifier: Development Status :: 5 - Production/Stable
Classifier: Environment :: Console
Classifier: Intended Audience :: Developers
Classifier: Intended Audience :: Information Technology
Classifier: Intended Audience :: Science/Research
Classifier: Intended Audience :: System Administrators
Classifier: License :: OSI Approved :: Apache Software License
Classifier: Operating System :: Microsoft :: Windows
Classifier: Operating System :: POSIX
Classifier: Programming Language :: Python :: 3.6
Classifier: Programming Language :: Python :: 3.7
Classifier: Programming Language :: Python :: 3.8
Classifier: Topic :: Software Development
Classifier: Topic :: System :: Distributed Computing
Classifier: Topic :: System :: Systems Administration
Requires-Python: >=3.6
License-File: LICENSE
